MANIFEST.in
README.rst
bootstrap.py
buildout.cfg
setup.py
t.py
t_write_read.py
configs/elliptics.conf
configs/ioserv.json
historydb/__init__.py
historydb/base_client.py
historydb/gevent_client.py
historydb/provider.py
historydb/threading_client.py
historydb.egg-info/PKG-INFO
historydb.egg-info/SOURCES.txt
historydb.egg-info/dependency_links.txt
historydb.egg-info/top_level.txt
tests/__init__.py
tests/base.py
tests/base_async_test.py
tests/server_runner.py
tests/test_failures.py
tests/test_gevent_support.py
tests/test_historydb.py
tests/test_threading_support.py