Metadata-Version: 1.1
Name: historydb
Version: 0.4.1
Summary: HistoryDB implemented in Python
Home-page: https://bitbucket.org/asdtech/historydb-python
Author: ASD Technologies
Author-email: admin@asdco.ru
License: BSD License
Platform: UNKNOWN
Classifier: License :: OSI Approved :: BSD License
Classifier: Development Status :: 4 - Beta
Classifier: Intended Audience :: Developers
Classifier: Topic :: Software Development :: Libraries :: Python Modules
Classifier: Programming Language :: Python
Classifier: Programming Language :: Python :: 2.6
Classifier: Programming Language :: Python :: 2.7
